{
  "products": [
    {
      "id": "xTMWfdv2Nlqv82vx4vTyD",
      "title": "شلوار",
      "price": "198000",
      "stock": "56",
      "rate": "80",
      "image": "./images/products/product-1.png"
    },
    {
      "id": "1",
      "title": "جوراب",
      "price": "198000",
      "stock": "56",
      "rate": "80",
      "image": "./images/products/product-1.png"
    },
    {
      "id": "2",
      "title": "جین",
      "price": "198000",
      "stock": "56",
      "rate": "80",
      "image": "./images/products/product-1.png"
    }
  ],
  "tikets": [
    {
      "id": "1",
      "image": "./images/users/user-1.jpg",
      "name": "Debra J. Wilson",
      "subject": "Your item has been updated!",
      "priority": "High",
      "status": "Open",
      "date": "01/04/2017",
      "exp": "21/05/2017"
    },
    {
      "id": "2",
      "image": "./images/users/user-1.jpg",
      "name": "ممد J. Wilson",
      "subject": "Your item has been updated!",
      "priority": "High",
      "status": "Open",
      "date": "01/04/2017",
      "exp": "21/05/2017"
    },
    {
      "id": "3",
      "image": "./images/users/user-1.jpg",
      "name": "علی J. Wilson",
      "subject": "Your item has been updated!",
      "priority": "High",
      "status": "Open",
      "date": "01/04/2017",
      "exp": "21/05/2017"
    },
    {
      "id": "4",
      "image": "./images/users/user-1.jpg",
      "name": "احمد J. Wilson",
      "subject": "Your item has been updated!",
      "priority": "High",
      "status": "Open",
      "date": "01/04/2017",
      "exp": "21/05/2017"
    },
    {
      "id": "5",
      "image": "./images/users/user-1.jpg",
      "name": "رضا J. Wilson",
      "subject": "Your item has been updated!",
      "priority": "High",
      "status": "Open",
      "date": "01/04/2017",
      "exp": "21/05/2017"
    }
  ],
  "users": [
    {
      "id": "E-wapynY4rA77yD1mZIum",
      "date": "7/15/2023",
      "name": "زهرا بهزادیخواه",
      "phone": "09032300793",
      "email": "behzadikhahzahra@gmail.com",
      "company": "ویراد",
      "caption": "سلام من زهرا بهزادیخواه هستم از مشهد و برنامه نویس فرانت اند هستم در شرکت ویر",
      "job": "برنامه نویسی فرانت اند",
      "image": "./images/users/user-1.jpg",
      "birthday": "29 شهریور 1379"
    },
    {
      "id": "E-4",
      "date": "7/15/2023",
      "name": "علی بهزادیخواه",
      "phone": "09032300793",
      "email": "behzadikhahzahra@gmail.com",
      "company": "ویراد",
      "caption": "سلام من زهرا بهزادیخواه هستم از مشهد و برنامه نویس فرانت اند هستم در شرکت ویر",
      "job": "برنامه نویسی فرانت اند",
      "image": "./images/users/user-1.jpg",
      "birthday": "29 شهریور 1379"
    },
    {
      "id": "E-2",
      "date": "7/15/2023",
      "name": "محمد بهزادیخواه",
      "phone": "09032300793",
      "email": "behzadikhahzahra@gmail.com",
      "company": "ویراد",
      "caption": "سلام من زهرا بهزادیخواه هستم از مشهد و برنامه نویس فرانت اند هستم در شرکت ویر",
      "job": "برنامه نویسی فرانت اند",
      "image": "./images/users/user-1.jpg",
      "birthday": "29 شهریور 1379"
    }
  ],
  "best-users": [
    {
      "id": "1",
      "image": "./images/users/user-2.jpg",
      "name": "هادی",
      "date": "عضو از 2017",
      "property": "BTC",
      "order": "0.00816117 BTC",
      "currency": "0.00097036 BTC"
    },
    {
      "id": "2",
      "image": "./images/users/user-4.jpg",
      "name": "امیر دانشیار",
      "date": "عضو از 2017",
      "property": "EUR",
      "order": "25.08 EUR",
      "currency": "12.58 EUR"
    },
    {
      "id": "3",
      "image": "./images/users/user-4.jpg",
      "name": "امیر دانشیار",
      "date": "عضو از 2017",
      "property": "EUR",
      "order": "25.08 EUR",
      "currency": "12.58 EUR"
    },
    {
      "id": "4",
      "image": "./images/users/user-5.jpg",
      "name": "مرتضی قاسم خانی    ",
      "date": "عضو از 2017",
      "property": "CNY",
      "order": "82.00 CNY",
      "currency": "30.83 CNY"
    },
    {
      "id": "5",
      "image": "./images/users/user-6.jpg",
      "name": "میثم جوادی    ",
      "date": "عضو از 2017",
      "property": "BTC",
      "order": "2.00816117 BTC",
      "currency": "1.00097036 BTC"
    }
  ],
  "revenue-history": [
    {
      "id": "1",
      "name": "تم مارکت",
      "date": "Oct 15, 2018",
      "pay": "$5848.68",
      "status": "معوق"
    },
    {
      "id": "2",
      "name": "شکربن",
      "date": "Oct 15, 2018",
      "pay": "$1247.25",
      "status": "پرداخت شده"
    },
    {
      "id": "3",
      "name": "شیرهولدینگ",
      "date": "Oct 15, 2018",
      "pay": "$815.89",
      "status": "پرداخت شده"
    },
    {
      "id": "4",
      "name": "امواتو",
      "date": "Oct 15, 2018",
      "pay": "$248.75",
      "status": "معوق"
    },
    {
      "id": "5",
      "name": "امواتو",
      "date": "Oct 15, 2018",
      "pay": "$248.75",
      "status": "معوق"
    },
    {
      "id": "6",
      "name": "ویسپهر",
      "date": "Oct 15, 2018",
      "pay": "$978.21",
      "status": "معوق"
    }
  ]
}
